machina_curiosa/__init__.py
machina_curiosa/githf.py
machina_curiosa/machina.yaml
machina_curiosa-0.0.1.dist-info/licenses/LICENSE
machina_curiosa-0.0.1.dist-info/METADATA
machina_curiosa-0.0.1.dist-info/WHEEL
machina_curiosa-0.0.1.dist-info/top_level.txt
machina_curiosa-0.0.1.dist-info/RECORD
