Metadata-Version: 2.4
Name: machina-curiosa
Version: 0.0.1
Summary: Curious machine.
Author-email: Alexander Fedotov <alex.fedotov@aol.com>
Project-URL: Homepage, https://github.com/machina-curiosa/machina-curiosa
Project-URL: Bug Tracker, https://github.com/machina-curiosa/machina-curiosa/issues
Classifier: Programming Language :: Python :: 3
Classifier: License :: OSI Approved :: MIT License
Classifier: Operating System :: OS Independent
Requires-Python: >=3.10
License-File: LICENSE
Requires-Dist: PyGithub>=2.6.1
Requires-Dist: PyYAML>=6.0.2
Dynamic: license-file
